{"file:///c%3A/%E5%AD%A6%E4%B9%A0/%E5%89%8D%E7%AB%AF/Teitter/src/main.ts":{"language":"TypeScript","code":13,"comment":0,"blank":4},"file:///c%3A/%E5%AD%A6%E4%B9%A0/%E5%89%8D%E7%AB%AF/Teitter/src/components/msgBox.vue":{"language":"vue","code":42,"comment":0,"blank":4},"file:///c%3A/%E5%AD%A6%E4%B9%A0/%E5%89%8D%E7%AB%AF/Teitter/src/api/index.ts":{"language":"TypeScript","code":409,"comment":20,"blank":30},"file:///c%3A/%E5%AD%A6%E4%B9%A0/%E5%89%8D%E7%AB%AF/Teitter/src/api/socket.ts":{"language":"TypeScript","code":11,"comment":0,"blank":4},"file:///c%3A/%E5%AD%A6%E4%B9%A0/%E5%89%8D%E7%AB%AF/Teitter/src/api/request.ts":{"language":"TypeScript","code":48,"comment":4,"blank":7},"file:///c%3A/%E5%AD%A6%E4%B9%A0/%E5%89%8D%E7%AB%AF/Teitter/src/components/editUserInfo.vue":{"language":"vue","code":400,"comment":7,"blank":14},"file:///c%3A/%E5%AD%A6%E4%B9%A0/%E5%89%8D%E7%AB%AF/Teitter/src/components/networkError.vue":{"language":"vue","code":35,"comment":0,"blank":3},"file:///c%3A/%E5%AD%A6%E4%B9%A0/%E5%89%8D%E7%AB%AF/Teitter/src/interfaces/pubInterface.ts":{"language":"TypeScript","code":93,"comment":0,"blank":5},"file:///c%3A/%E5%AD%A6%E4%B9%A0/%E5%89%8D%E7%AB%AF/Teitter/src/router/index.ts":{"language":"TypeScript","code":132,"comment":0,"blank":6},"file:///c%3A/%E5%AD%A6%E4%B9%A0/%E5%89%8D%E7%AB%AF/Teitter/src/components/login/theRegister.vue":{"language":"vue","code":154,"comment":0,"blank":16},"file:///c%3A/%E5%AD%A6%E4%B9%A0/%E5%89%8D%E7%AB%AF/Teitter/src/components/imgClipper.vue":{"language":"vue","code":506,"comment":0,"blank":19},"file:///c%3A/%E5%AD%A6%E4%B9%A0/%E5%89%8D%E7%AB%AF/Teitter/src/components/noticeCard.vue":{"language":"vue","code":150,"comment":0,"blank":8},"file:///c%3A/%E5%AD%A6%E4%B9%A0/%E5%89%8D%E7%AB%AF/Teitter/src/style/main.less":{"language":"Less","code":24,"comment":2,"blank":4},"file:///c%3A/%E5%AD%A6%E4%B9%A0/%E5%89%8D%E7%AB%AF/Teitter/src/components/aside/userInfoCard.vue":{"language":"vue","code":125,"comment":0,"blank":6},"file:///c%3A/%E5%AD%A6%E4%B9%A0/%E5%89%8D%E7%AB%AF/Teitter/src/components/login/theLogin.vue":{"language":"vue","code":107,"comment":0,"blank":12},"file:///c%3A/%E5%AD%A6%E4%B9%A0/%E5%89%8D%E7%AB%AF/Teitter/src/utils/index.ts":{"language":"TypeScript","code":63,"comment":13,"blank":3},"file:///c%3A/%E5%AD%A6%E4%B9%A0/%E5%89%8D%E7%AB%AF/Teitter/src/components/aside/theAside.vue":{"language":"vue","code":214,"comment":0,"blank":10},"file:///c%3A/%E5%AD%A6%E4%B9%A0/%E5%89%8D%E7%AB%AF/Teitter/src/components/statusPanel.vue":{"language":"vue","code":158,"comment":0,"blank":9},"file:///c%3A/%E5%AD%A6%E4%B9%A0/%E5%89%8D%E7%AB%AF/Teitter/src/components/theBanner.vue":{"language":"vue","code":83,"comment":0,"blank":4},"file:///c%3A/%E5%AD%A6%E4%B9%A0/%E5%89%8D%E7%AB%AF/Teitter/src/stores/teitter.ts":{"language":"TypeScript","code":44,"comment":1,"blank":5},"file:///c%3A/%E5%AD%A6%E4%B9%A0/%E5%89%8D%E7%AB%AF/Teitter/src/components/mainArea/theMainArea.vue":{"language":"vue","code":94,"comment":0,"blank":8},"file:///c%3A/%E5%AD%A6%E4%B9%A0/%E5%89%8D%E7%AB%AF/Teitter/src/components/mainArea/theTeitterCard.vue":{"language":"vue","code":390,"comment":2,"blank":20},"file:///c%3A/%E5%AD%A6%E4%B9%A0/%E5%89%8D%E7%AB%AF/Teitter/src/components/mainArea/publishTeitter.vue":{"language":"vue","code":360,"comment":0,"blank":26},"file:///c%3A/%E5%AD%A6%E4%B9%A0/%E5%89%8D%E7%AB%AF/Teitter/src/components/theLoad.vue":{"language":"vue","code":24,"comment":0,"blank":4},"file:///c%3A/%E5%AD%A6%E4%B9%A0/%E5%89%8D%E7%AB%AF/Teitter/src/font/iconfont.css":{"language":"CSS","code":85,"comment":0,"blank":27},"file:///c%3A/%E5%AD%A6%E4%B9%A0/%E5%89%8D%E7%AB%AF/Teitter/src/components/tweet/commentCard.vue":{"language":"vue","code":316,"comment":1,"blank":19},"file:///c%3A/%E5%AD%A6%E4%B9%A0/%E5%89%8D%E7%AB%AF/Teitter/src/components/tweet/shareCard.vue":{"language":"vue","code":82,"comment":0,"blank":4},"file:///c%3A/%E5%AD%A6%E4%B9%A0/%E5%89%8D%E7%AB%AF/Teitter/src/components/tweet/comment.vue":{"language":"vue","code":121,"comment":0,"blank":5},"file:///c%3A/%E5%AD%A6%E4%B9%A0/%E5%89%8D%E7%AB%AF/Teitter/src/App.vue":{"language":"vue","code":44,"comment":0,"blank":6},"file:///c%3A/%E5%AD%A6%E4%B9%A0/%E5%89%8D%E7%AB%AF/Teitter/src/font/demo_index.html":{"language":"HTML","code":651,"comment":2,"blank":88},"file:///c%3A/%E5%AD%A6%E4%B9%A0/%E5%89%8D%E7%AB%AF/Teitter/src/font/iconfont.json":{"language":"JSON","code":177,"comment":0,"blank":1},"file:///c%3A/%E5%AD%A6%E4%B9%A0/%E5%89%8D%E7%AB%AF/Teitter/src/font/demo.css":{"language":"CSS","code":435,"comment":19,"blank":86},"file:///c%3A/%E5%AD%A6%E4%B9%A0/%E5%89%8D%E7%AB%AF/Teitter/src/views/homePageView/accountView.vue":{"language":"vue","code":321,"comment":0,"blank":16},"file:///c%3A/%E5%AD%A6%E4%B9%A0/%E5%89%8D%E7%AB%AF/Teitter/src/views/loginView/register.vue":{"language":"vue","code":9,"comment":0,"blank":3},"file:///c%3A/%E5%AD%A6%E4%B9%A0/%E5%89%8D%E7%AB%AF/Teitter/src/views/homePageView/mainView.vue":{"language":"vue","code":64,"comment":0,"blank":5},"file:///c%3A/%E5%AD%A6%E4%B9%A0/%E5%89%8D%E7%AB%AF/Teitter/src/font/iconfont.js":{"language":"JavaScript","code":1,"comment":0,"blank":0},"file:///c%3A/%E5%AD%A6%E4%B9%A0/%E5%89%8D%E7%AB%AF/Teitter/src/css/main.css":{"language":"CSS","code":22,"comment":0,"blank":1},"file:///c%3A/%E5%AD%A6%E4%B9%A0/%E5%89%8D%E7%AB%AF/Teitter/src/views/loginView/loginView.vue":{"language":"vue","code":9,"comment":0,"blank":3},"file:///c%3A/%E5%AD%A6%E4%B9%A0/%E5%89%8D%E7%AB%AF/Teitter/src/components/tweet/tweetInfoCard.vue":{"language":"vue","code":358,"comment":1,"blank":16},"file:///c%3A/%E5%AD%A6%E4%B9%A0/%E5%89%8D%E7%AB%AF/Teitter/src/views/homePageView/homePageView.vue":{"language":"vue","code":7,"comment":0,"blank":3},"file:///c%3A/%E5%AD%A6%E4%B9%A0/%E5%89%8D%E7%AB%AF/Teitter/src/views/homePageView/noticeView.vue":{"language":"vue","code":108,"comment":0,"blank":8},"file:///c%3A/%E5%AD%A6%E4%B9%A0/%E5%89%8D%E7%AB%AF/Teitter/src/views/homePageView/emailView.vue":{"language":"vue","code":27,"comment":0,"blank":3},"file:///c%3A/%E5%AD%A6%E4%B9%A0/%E5%89%8D%E7%AB%AF/Teitter/src/views/loginView/loginRegisterView.vue":{"language":"vue","code":68,"comment":0,"blank":3},"file:///c%3A/%E5%AD%A6%E4%B9%A0/%E5%89%8D%E7%AB%AF/Teitter/src/views/homePageView/tweetInfoView.vue":{"language":"vue","code":85,"comment":0,"blank":9},"file:///c%3A/%E5%AD%A6%E4%B9%A0/%E5%89%8D%E7%AB%AF/Teitter/src/views/homePageView/searchView.vue":{"language":"vue","code":144,"comment":0,"blank":10},"file:///c%3A/%E5%AD%A6%E4%B9%A0/%E5%89%8D%E7%AB%AF/Teitter/src/views/homePageView/follow/follower.vue":{"language":"vue","code":42,"comment":0,"blank":3},"file:///c%3A/%E5%AD%A6%E4%B9%A0/%E5%89%8D%E7%AB%AF/Teitter/src/views/homePageView/follow/followView.vue":{"language":"vue","code":124,"comment":0,"blank":8},"file:///c%3A/%E5%AD%A6%E4%B9%A0/%E5%89%8D%E7%AB%AF/Teitter/src/views/homePageView/follow/following.vue":{"language":"vue","code":39,"comment":0,"blank":3},"file:///c%3A/%E5%AD%A6%E4%B9%A0/%E5%89%8D%E7%AB%AF/Teitter/src/views/homePageView/follow/userCard.vue":{"language":"vue","code":61,"comment":0,"blank":3}}